[{"id":"43","listID":"PLY27cJTUBR0tGFLrLcR9VDKfNyNwFnY7B","listName":"OWI 1 - Video corso di italiano","categoryID":"8","imageKey":"PUnnVNzaf0I","countVideos":"400"},{"id":"44","listID":"PLfzlm72DZO3KgQyx8G4E5NF9rYikj6QCc","listName":"Pronomi Indiretti","categoryID":"8","imageKey":"ugxLi3XVx_c","countVideos":"98"},{"id":"45","listID":"PLPXzrP5TJA187UToWmcITiHKjru0e8BbQ","listName":"La canzone dellalfabeto italiano (KARAOKE) | Italiano per bambini con ALMA Edizioni","categoryID":"8","imageKey":"V78zmzVyNpM","countVideos":"150"},{"id":"46","listID":"PL59GcrPDHI8JimcXIKCqBKNbWbD9IqTNB","listName":"Video lezioni di grammatica - Come si usano i segni di interpunzione?","categoryID":"8","imageKey":"CICi9PqlKhk","countVideos":"100"},{"id":"47","listID":"PL52573CC08D592E29","listName":"editoria ITALIANO PER STRANIERI digital decoupage","categoryID":"8","imageKey":"pFK8oFgiZOE","countVideos":"70"},{"id":"48","listID":"PLwXSwhDjyULZHlJHFejUnWj_kSrNbpeLS","listName":"Italiano lezione 12 - Impariamo i numeri da 30 a 100 [Curs de Limba italian\u0103]","categoryID":"8","imageKey":"bMAuGX0YzV8","countVideos":"11"},{"id":"49","listID":"PLblWP9mVfHG0uqFdSpFJ5-SJu8BMuBwDK","listName":"ITALIAN CONVERSATION LEVEL II","categoryID":"8","imageKey":"F9_1KWI1E3c","countVideos":"49"},{"id":"50","listID":"PLwXSwhDjyULaCIS50GwlcdCJul--vlqSr","listName":"Italiano lezione 15 - Impariamo la punteggiatura [Curs de Limba italian\u0103]","categoryID":"8","imageKey":"-PRsJQtmabw","countVideos":"7"},{"id":"51","listID":"PL64PKo3J4BTfhRVDoUWCL5nloOq8SouRl","listName":"In treno -  Dialogo. Verbo essere","categoryID":"8","imageKey":"2IurMN15bL8","countVideos":"21"},{"id":"52","listID":"PLS2IdqjJNYz_7oDbRruhMzTzpeZk-z4Ka","listName":"OWI - Introduzione Livello B1 (Intermedio)","categoryID":"8","imageKey":"pIUQdxemJPU","countVideos":"27"}]