[{"id":"2016","videoID":"-UbHYttXZCQ","videosName":"Piove - Lorenzo Jovanotti Cherubini","videoDuration":"00:03:16","getFromList":"PLGsen7tKtEgDJlllSRzVO6sDNUXT6yXdI","categoryID":"10"},{"id":"2017","videoID":"D1ZYhVpdXbQ","videosName":"Singing In The Rain - Singing In The Rain (Gene Kelly) [HD Widescreen]","videoDuration":"00:04:36","getFromList":"PLGsen7tKtEgDJlllSRzVO6sDNUXT6yXdI","categoryID":"10"},{"id":"2018","videoID":"zP9KWG-Y5OM","videosName":"NEGRAMARO - Cade la pioggia (video ufficiale)","videoDuration":"00:06:09","getFromList":"PLGsen7tKtEgDJlllSRzVO6sDNUXT6yXdI","categoryID":"10"},{"id":"2019","videoID":"EABsrr8e2fQ","videosName":"Vinicio Capossela - Canzoni a Manovella 2000 - Nella Pioggia","videoDuration":"00:03:53","getFromList":"PLGsen7tKtEgDJlllSRzVO6sDNUXT6yXdI","categoryID":"10"},{"id":"2020","videoID":"B52rYdj5QiA","videosName":"Rain and Tears - Aphrodites Child","videoDuration":"00:03:13","getFromList":"PLGsen7tKtEgDJlllSRzVO6sDNUXT6yXdI","categoryID":"10"},{"id":"2021","videoID":"hziG9Nr6KHU","videosName":"B.J.Thomas - Raindrops Keep Fallin On My Head","videoDuration":"00:02:59","getFromList":"PLGsen7tKtEgDJlllSRzVO6sDNUXT6yXdI","categoryID":"10"},{"id":"2022","videoID":"VQE47heXQKw","videosName":"Vinicio Capossela - Pioggia di novembre","videoDuration":"00:06:16","getFromList":"PLGsen7tKtEgDJlllSRzVO6sDNUXT6yXdI","categoryID":"10"}]